setup.py
okscraper/__init__.py
okscraper/base.py
okscraper/sources.py
okscraper/storages.py
okscraper.egg-info/PKG-INFO
okscraper.egg-info/SOURCES.txt
okscraper.egg-info/dependency_links.txt
okscraper.egg-info/requires.txt
okscraper.egg-info/top_level.txt
okscraper/cli/__init__.py
okscraper/cli/runner.py
okscraper/tests/__init__.py
okscraper/tests/testBase.py
okscraper/tests/testCli.py
okscraper/tests/mock_module/__init__.py
okscraper/tests/mock_module/scrapers.py