Metadata-Version: 1.0
Name: okscraper
Version: 0.0.7
Summary: module for scraping websites and documents
Home-page: https://github.com/hasadna/okscraper
Author: Ori Hoch
Author-email: ori@uumpa.com
License: GPLv3
Platform: UNKNOWN
